django_uaccounts-0.1.7.dist-info/DESCRIPTION.rst
django_uaccounts-0.1.7.dist-info/METADATA
django_uaccounts-0.1.7.dist-info/RECORD
django_uaccounts-0.1.7.dist-info/WHEEL
django_uaccounts-0.1.7.dist-info/metadata.json
django_uaccounts-0.1.7.dist-info/top_level.txt
uaccounts/__init__.py
uaccounts/admin.py
uaccounts/decorators.py
uaccounts/forms.py
uaccounts/models.py
uaccounts/settings.py
uaccounts/urls.py
uaccounts/utils.py
uaccounts/views.py
uaccounts/static/uaccounts/css/edit.css
uaccounts/static/uaccounts/css/forgot.css
uaccounts/static/uaccounts/css/form.css
uaccounts/static/uaccounts/css/index.css
uaccounts/static/uaccounts/css/profile.css
uaccounts/static/uaccounts/css/style.css
uaccounts/static/uaccounts/js/edit.js
uaccounts/static/uaccounts/js/jquery-2.1.4.min.js
uaccounts/static/uaccounts/js/js.cookie.js
uaccounts/templates/uaccounts/activated.html
uaccounts/templates/uaccounts/activation.txt
uaccounts/templates/uaccounts/base.html
uaccounts/templates/uaccounts/change.html
uaccounts/templates/uaccounts/changed.html
uaccounts/templates/uaccounts/edit.html
uaccounts/templates/uaccounts/forgot.html
uaccounts/templates/uaccounts/forgot.txt
uaccounts/templates/uaccounts/forgotsent.html
uaccounts/templates/uaccounts/index.html
uaccounts/templates/uaccounts/login.html
uaccounts/templates/uaccounts/pending.html
uaccounts/templates/uaccounts/register.html
uaccounts/templates/uaccounts/verified.html
uaccounts/templates/uaccounts/verify.txt
