Metadata-Version: 2.0
Name: django-uaccounts
Version: 0.1.7
Summary: Pluggable user accounts and profiles
Home-page: https://github.com/amikrop/django-uaccounts
Author: Aristotelis Mikropoulos
Author-email: amikrop@gmail.com
License: BSD
Download-URL: https://github.com/amikrop/django-uaccounts
Platform: UNKNOWN
Classifier: Environment :: Web Environment
Classifier: Framework :: Django
Classifier: Intended Audience :: Developers
Classifier: License :: OSI Approved :: BSD License
Classifier: Operating System :: OS Independent
Classifier: Programming Language :: Python
Classifier: Topic :: Internet :: WWW/HTTP
Classifier: Topic :: Internet :: WWW/HTTP :: Dynamic Content
